st_mui_dialog/__init__.py
st_mui_dialog/frontend/build/asset-manifest.json
st_mui_dialog/frontend/build/bootstrap.min.css
st_mui_dialog/frontend/build/index.html
st_mui_dialog/frontend/build/precache-manifest.17d8705fd053d77488853f8f4d2c1dac.js
st_mui_dialog/frontend/build/precache-manifest.749fcf65629b5187370f3cc3c9993a32.js
st_mui_dialog/frontend/build/service-worker.js
st_mui_dialog/frontend/build/static/js/2.0fce2338.chunk.js
st_mui_dialog/frontend/build/static/js/2.0fce2338.chunk.js.LICENSE.txt
st_mui_dialog/frontend/build/static/js/2.0fce2338.chunk.js.map
st_mui_dialog/frontend/build/static/js/2.f12f026f.chunk.js
st_mui_dialog/frontend/build/static/js/2.f12f026f.chunk.js.LICENSE.txt
st_mui_dialog/frontend/build/static/js/2.f12f026f.chunk.js.map
st_mui_dialog/frontend/build/static/js/main.00ade12e.chunk.js
st_mui_dialog/frontend/build/static/js/main.00ade12e.chunk.js.map
st_mui_dialog/frontend/build/static/js/main.8bd25ac0.chunk.js
st_mui_dialog/frontend/build/static/js/main.8bd25ac0.chunk.js.map
st_mui_dialog/frontend/build/static/js/runtime-main.7050f38a.js
st_mui_dialog/frontend/build/static/js/runtime-main.7050f38a.js.map
st_mui_dialog-0.0.10.dist-info/METADATA
st_mui_dialog-0.0.10.dist-info/WHEEL
st_mui_dialog-0.0.10.dist-info/top_level.txt
st_mui_dialog-0.0.10.dist-info/RECORD
