Metadata-Version: 2.1
Name: st-mui-dialog
Version: 0.0.10
Summary: Streamlit Component for MUI Dialogs
Home-page: 
Author: 
Author-email: 
Requires-Python: >=3.6
Requires-Dist: streamlit (>=0.63)
